[{"id":"e00b6f82-8ab7-4893-958e-d9ef4c5f9b34","date":"2005","pkd":"50","pkd_name":"TRANSPORT WODNY","year":"2005","revenue":2659.64,"net_profit":110.54,"investments":67.62,"firms":54,"profitable_firms":41,"profit_margin":0.04156201591192794,"profitable_share":0.7592592592592593,"bank_debt":94.44,"total_liab":1001.71,"leverage_bank_to_rev":0.0355085650689567,"leverage_tot_to_rev":0.3766336797461311,"invest_intensity":0.025424493540479164,"cagr_revenue":null,"cagr_net_profit":null,"cagr_investments":null,"cagr_firms":null,"profit_margin_std_3y":null,"size_index":0.2567750015760082,"growth_index":null,"profit_index":79.91876284511906,"risk_index":62.59974428506855,"outlook_index":1.0779751132806652,"current_index":38.81096899711553,"future_index":19.21111333083283,"main_index":30.97102673060245,"class1":null,"revenue_parameter":null,"firms_parameter":null,"growth_parameter":null,"cagr_revenue_parameter":null,"cagr_net_profit_parameter":null,"profit_margin_parameter":null,"profitable_share_parameter":null,"leverage_bank_to_rev_parameter":null,"leverage_tot_to_rev_parameter":null,"profit_margin_std_3y_parameter":null,"invest_intensity_parameter":null,"cagr_investments_parameter":null,"size_index_parameter":null,"growth_index_parameter":null,"profit_index_parameter":null,"risk_index_parameter":null,"growth_index_parameter2":null,"profit_index_parameter2":null,"risk_index_parameter2":null,"future_growth_index_parameter":null,"outlook_index_parameter":null,"future_risk_index_parameter":null,"current_index_parameter":null,"future_index_parameter":null,"prediction":null},{"id":"41db2655-ba16-40ea-b638-f7003b4c2a34","date":"2006","pkd":"50","pkd_name":"TRANSPORT WODNY","year":"2006","revenue":2628.26,"net_profit":101.32,"investments":29.159999999999997,"firms":52,"profitable_firms":32,"profit_margin":0.038550219536879905,"profitable_share":0.6153846153846154,"bank_debt":81.47,"total_liab":943.63,"leverage_bank_to_rev":0.03099769429204112,"leverage_tot_to_rev":0.35903221142504926,"invest_intensity":0.011094792752619601,"cagr_revenue":null,"cagr_net_profit":null,"cagr_investments":null,"cagr_firms":null,"profit_margin_std_3y":0.0021296616403495253,"size_index":0.24009050041898333,"growth_index":null,"profit_index":49.89928814886892,"risk_index":96.27568040921776,"outlook_index":0.4411418800019681,"current_index":41.40554426006635,"future_index":29.059160874766114,"main_index":36.466990905946254,"class1":null,"revenue_parameter":null,"firms_parameter":null,"growth_parameter":null,"cagr_revenue_parameter":null,"cagr_net_profit_parameter":null,"profit_margin_parameter":null,"profitable_share_parameter":null,"leverage_bank_to_rev_parameter":null,"leverage_tot_to_rev_parameter":null,"profit_margin_std_3y_parameter":null,"invest_intensity_parameter":null,"cagr_investments_parameter":null,"size_index_parameter":null,"growth_index_parameter":null,"profit_index_parameter":null,"risk_index_parameter":null,"growth_index_parameter2":null,"profit_index_parameter2":null,"risk_index_parameter2":null,"future_growth_index_parameter":null,"outlook_index_parameter":null,"future_risk_index_parameter":null,"current_index_parameter":null,"future_index_parameter":null,"prediction":null},{"id":"92bdd700-4c0f-4586-a519-2f7e7d03025f","date":"2007","pkd":"50","pkd_name":"TRANSPORT WODNY","year":"2007","revenue":2686.89,"net_profit":163.26999999999998,"investments":77.92,"firms":52,"profitable_firms":39,"profit_margin":0.06076542024422287,"profitable_share":0.75,"bank_debt":81.72,"total_liab":887.9300000000001,"leverage_bank_to_rev":0.030414345209517323,"leverage_tot_to_rev":0.33046756659185905,"invest_intensity":0.02900007071372479,"cagr_revenue":null,"cagr_net_profit":null,"cagr_investments":null,"cagr_firms":null,"profit_margin_std_3y":0.01205098058127697,"size_index":0.22869166068356198,"growth_index":null,"profit_index":77.00128616046999,"risk_index":95.85483303964465,"outlook_index":1.065523802759387,"current_index":48.0525097841476,"future_index":29.18265943299715,"main_index":40.50456964368742,"class1":null,"revenue_parameter":null,"firms_parameter":null,"growth_parameter":null,"cagr_revenue_parameter":null,"cagr_net_profit_parameter":null,"profit_margin_parameter":null,"profitable_share_parameter":null,"leverage_bank_to_rev_parameter":null,"leverage_tot_to_rev_parameter":null,"profit_margin_std_3y_parameter":null,"invest_intensity_parameter":null,"cagr_investments_parameter":null,"size_index_parameter":null,"growth_index_parameter":null,"profit_index_parameter":null,"risk_index_parameter":null,"growth_index_parameter2":null,"profit_index_parameter2":null,"risk_index_parameter2":null,"future_growth_index_parameter":null,"outlook_index_parameter":null,"future_risk_index_parameter":null,"current_index_parameter":null,"future_index_parameter":null,"prediction":null},{"id":"f9572e87-a712-4158-ade2-36877d2b8b58","date":"2008","pkd":"50","pkd_name":"TRANSPORT WODNY","year":"2008","revenue":1298.02,"net_profit":-85.51,"investments":121.99000000000001,"firms":54,"profitable_firms":11,"profit_margin":-0.06587725921018167,"profitable_share":0.2037037037037037,"bank_debt":433.53,"total_liab":1207.03,"leverage_bank_to_rev":0.3339933128919431,"leverage_tot_to_rev":0.9299009260257931,"invest_intensity":0.09398160274880203,"cagr_revenue":-0.2126771738554486,"cagr_net_profit":-0.5911887099692419,"cagr_investments":0.21735250838625997,"cagr_firms":0,"profit_margin_std_3y":0.06762270540694472,"size_index":0.15897361864875253,"growth_index":54.482021581026885,"profit_index":18.25055931476379,"risk_index":80.41307415600099,"outlook_index":28.864084753293717,"current_index":42.33886219447771,"future_index":52.01416262242584,"main_index":46.208982365656965,"class1":null,"revenue_parameter":null,"firms_parameter":null,"growth_parameter":null,"cagr_revenue_parameter":null,"cagr_net_profit_parameter":null,"profit_margin_parameter":null,"profitable_share_parameter":null,"leverage_bank_to_rev_parameter":null,"leverage_tot_to_rev_parameter":null,"profit_margin_std_3y_parameter":null,"invest_intensity_parameter":null,"cagr_investments_parameter":null,"size_index_parameter":null,"growth_index_parameter":null,"profit_index_parameter":null,"risk_index_parameter":null,"growth_index_parameter2":null,"profit_index_parameter2":null,"risk_index_parameter2":null,"future_growth_index_parameter":null,"outlook_index_parameter":null,"future_risk_index_parameter":null,"current_index_parameter":null,"future_index_parameter":null,"prediction":null},{"id":"4866f738-5491-4c65-accb-6691c93f527d","date":"2009","pkd":"50","pkd_name":"TRANSPORT WODNY","year":"2009","revenue":1864.52,"net_profit":-6.59,"investments":51.41,"firms":50,"profitable_firms":30,"profit_margin":-0.0035344217278441637,"profitable_share":0.6,"bank_debt":895.94,"total_liab":2126.45,"leverage_bank_to_rev":0.48052045566687407,"leverage_tot_to_rev":1.1404811962328105,"invest_intensity":0.027572780125716,"cagr_revenue":-0.10813407053398383,"cagr_net_profit":-0.35501381760757994,"cagr_investments":0.2080549654071291,"cagr_firms":-0.012988483125714434,"profit_margin_std_3y":0.06332385980335928,"size_index":0.1758466530874137,"growth_index":19.35094114773579,"profit_index":40.996695226715545,"risk_index":76.7899153690683,"outlook_index":23.524324031995192,"current_index":38.1590530349508,"future_index":38.2519865678393,"main_index":38.1962264481062,"class1":null,"revenue_parameter":null,"firms_parameter":null,"growth_parameter":null,"cagr_revenue_parameter":null,"cagr_net_profit_parameter":null,"profit_margin_parameter":null,"profitable_share_parameter":null,"leverage_bank_to_rev_parameter":null,"leverage_tot_to_rev_parameter":null,"profit_margin_std_3y_parameter":null,"invest_intensity_parameter":null,"cagr_investments_parameter":null,"size_index_parameter":null,"growth_index_parameter":null,"profit_index_parameter":null,"risk_index_parameter":null,"growth_index_parameter2":null,"profit_index_parameter2":null,"risk_index_parameter2":null,"future_growth_index_parameter":null,"outlook_index_parameter":null,"future_risk_index_parameter":null,"current_index_parameter":null,"future_index_parameter":null,"prediction":null},{"id":"15a843e3-4afa-4d6c-89a0-f0864a0984df","date":"2010","pkd":"50","pkd_name":"TRANSPORT WODNY","year":"2010","revenue":1563.33,"net_profit":9.639999999999999,"investments":44.07,"firms":50,"profitable_firms":26,"profit_margin":0.006166324448452981,"profitable_share":0.52,"bank_debt":802.05,"total_liab":1906.3400000000001,"leverage_bank_to_rev":0.5130394734317131,"leverage_tot_to_rev":1.2194098494879522,"invest_intensity":0.028189825564660053,"cagr_revenue":-0.16516574968442455,"cagr_net_profit":-0.6106051407448454,"cagr_investments":-0.17301423216299316,"cagr_firms":-0.012988483125714434,"profit_margin_std_3y":0.039096060773656766,"size_index":0.16151240912121906,"growth_index":51.321378337593835,"profit_index":44.37846504401686,"risk_index":72.15100916161347,"outlook_index":16.339690401641136,"current_index":45.60256607571096,"future_index":43.577592410418646,"main_index":44.792576609594036,"class1":null,"revenue_parameter":null,"firms_parameter":null,"growth_parameter":null,"cagr_revenue_parameter":null,"cagr_net_profit_parameter":null,"profit_margin_parameter":null,"profitable_share_parameter":null,"leverage_bank_to_rev_parameter":null,"leverage_tot_to_rev_parameter":null,"profit_margin_std_3y_parameter":null,"invest_intensity_parameter":null,"cagr_investments_parameter":null,"size_index_parameter":null,"growth_index_parameter":null,"profit_index_parameter":null,"risk_index_parameter":null,"growth_index_parameter2":null,"profit_index_parameter2":null,"risk_index_parameter2":null,"future_growth_index_parameter":null,"outlook_index_parameter":null,"future_risk_index_parameter":null,"current_index_parameter":null,"future_index_parameter":null,"prediction":null},{"id":"bcb62dbd-3fc1-4daf-a625-7d39e996b005","date":"2011","pkd":"50","pkd_name":"TRANSPORT WODNY","year":"2011","revenue":605.09,"net_profit":-42.39,"investments":168.91,"firms":58,"profitable_firms":9,"profit_margin":-0.07005569419425209,"profitable_share":0.15517241379310345,"bank_debt":860.64,"total_liab":1006.1100000000001,"leverage_bank_to_rev":1.422333867689104,"leverage_tot_to_rev":1.6627443851327903,"invest_intensity":0.27914855641309555,"cagr_revenue":-0.22462309027527116,"cagr_net_profit":0.16808950220247146,"cagr_investments":0.1145777699228625,"cagr_firms":0.0241056085619491,"profit_margin_std_3y":0.041490923290313154,"size_index":0.14413360029597694,"growth_index":35.22509178900097,"profit_index":39.40842291437419,"risk_index":70.91876519536137,"outlook_index":33.388399891963935,"current_index":39.96283495451139,"future_index":45.198517052094275,"main_index":42.057107793544546,"class1":null,"revenue_parameter":null,"firms_parameter":null,"growth_parameter":null,"cagr_revenue_parameter":null,"cagr_net_profit_parameter":null,"profit_margin_parameter":null,"profitable_share_parameter":null,"leverage_bank_to_rev_parameter":null,"leverage_tot_to_rev_parameter":null,"profit_margin_std_3y_parameter":null,"invest_intensity_parameter":null,"cagr_investments_parameter":null,"size_index_parameter":null,"growth_index_parameter":null,"profit_index_parameter":null,"risk_index_parameter":null,"growth_index_parameter2":null,"profit_index_parameter2":null,"risk_index_parameter2":null,"future_growth_index_parameter":null,"outlook_index_parameter":null,"future_risk_index_parameter":null,"current_index_parameter":null,"future_index_parameter":null,"prediction":null},{"id":"ecb25a58-d54f-4b3e-bcac-1074078fd314","date":"2012","pkd":"50","pkd_name":"TRANSPORT WODNY","year":"2012","revenue":690.46,"net_profit":73.07,"investments":52.5,"firms":52,"profitable_firms":12,"profit_margin":0.10582799872548734,"profitable_share":0.23076923076923078,"bank_debt":754.35,"total_liab":858.27,"leverage_bank_to_rev":1.0925325145555136,"leverage_tot_to_rev":1.243040871303189,"invest_intensity":0.07603626567795382,"cagr_revenue":-0.28189079690683094,"cagr_net_profit":4.029337379868488,"cagr_investments":0.007017999386572882,"cagr_firms":0.013159403820177218,"profit_margin_std_3y":0.08820177519071047,"size_index":0.1300232659492823,"growth_index":38.53571277844855,"profit_index":41.29443055061476,"risk_index":74.83735960681042,"outlook_index":5.949012543120556,"current_index":42.43474836749881,"future_index":36.39152673282591,"main_index":40.01745971362965,"class1":null,"revenue_parameter":null,"firms_parameter":null,"growth_parameter":null,"cagr_revenue_parameter":null,"cagr_net_profit_parameter":null,"profit_margin_parameter":null,"profitable_share_parameter":null,"leverage_bank_to_rev_parameter":null,"leverage_tot_to_rev_parameter":null,"profit_margin_std_3y_parameter":null,"invest_intensity_parameter":null,"cagr_investments_parameter":null,"size_index_parameter":null,"growth_index_parameter":null,"profit_index_parameter":null,"risk_index_parameter":null,"growth_index_parameter2":null,"profit_index_parameter2":null,"risk_index_parameter2":null,"future_growth_index_parameter":null,"outlook_index_parameter":null,"future_risk_index_parameter":null,"current_index_parameter":null,"future_index_parameter":null,"prediction":null},{"id":"407e9ab0-393e-434b-ad38-d82baddc7dd1","date":"2013","pkd":"50","pkd_name":"TRANSPORT WODNY","year":"2013","revenue":457.71000000000004,"net_profit":8.23,"investments":30.58,"firms":56,"profitable_firms":13,"profit_margin":0.01798081754822923,"profitable_share":0.23214285714285715,"bank_debt":175.71,"total_liab":234.65000000000003,"leverage_bank_to_rev":0.38388936225994624,"leverage_tot_to_rev":0.5126608551266086,"invest_intensity":0.06681086277337178,"cagr_revenue":-0.335981907139815,"cagr_net_profit":-0.05134652822477359,"cagr_investments":-0.11468434576791087,"cagr_firms":0.03849882037022079,"profit_margin_std_3y":0.08794186344365924,"size_index":0.12709854304945215,"growth_index":14.608781982546963,"profit_index":31.490574617890704,"risk_index":86.92193428078744,"outlook_index":5.2558662929570055,"current_index":37.62683914295554,"future_index":32.56156139618312,"main_index":35.60072804424657,"class1":null,"revenue_parameter":null,"firms_parameter":null,"growth_parameter":null,"cagr_revenue_parameter":null,"cagr_net_profit_parameter":null,"profit_margin_parameter":null,"profitable_share_parameter":null,"leverage_bank_to_rev_parameter":null,"leverage_tot_to_rev_parameter":null,"profit_margin_std_3y_parameter":null,"invest_intensity_parameter":null,"cagr_investments_parameter":null,"size_index_parameter":null,"growth_index_parameter":null,"profit_index_parameter":null,"risk_index_parameter":null,"growth_index_parameter2":null,"profit_index_parameter2":null,"risk_index_parameter2":null,"future_growth_index_parameter":null,"outlook_index_parameter":null,"future_risk_index_parameter":null,"current_index_parameter":null,"future_index_parameter":null,"prediction":null},{"id":"41933f4f-15f7-4860-974f-8554d49c8e54","date":"2014","pkd":"50","pkd_name":"TRANSPORT WODNY","year":"2014","revenue":1998.23,"net_profit":265.82,"investments":19.25,"firms":60,"profitable_firms":44,"profit_margin":0.13302772954064346,"profitable_share":0.7333333333333333,"bank_debt":914.1000000000001,"total_liab":1341.18,"leverage_bank_to_rev":0.45745484754007304,"leverage_tot_to_rev":0.6711839978380867,"invest_intensity":0.009633525670218144,"cagr_revenue":0.4891616145535549,"cagr_net_profit":2.4236061964299753,"cagr_investments":-0.5151674260465409,"cagr_firms":0.01136460926688998,"profit_margin_std_3y":0.06012867390881724,"size_index":0.17915579388166386,"growth_index":24.12407514363309,"profit_index":90.39687708432649,"risk_index":79.18938473875554,"outlook_index":0.47273122450751287,"current_index":52.42288463739288,"future_index":31.18313045451959,"main_index":43.926982964243564,"class1":null,"revenue_parameter":null,"firms_parameter":null,"growth_parameter":null,"cagr_revenue_parameter":null,"cagr_net_profit_parameter":null,"profit_margin_parameter":null,"profitable_share_parameter":null,"leverage_bank_to_rev_parameter":null,"leverage_tot_to_rev_parameter":null,"profit_margin_std_3y_parameter":null,"invest_intensity_parameter":null,"cagr_investments_parameter":null,"size_index_parameter":null,"growth_index_parameter":null,"profit_index_parameter":null,"risk_index_parameter":null,"growth_index_parameter2":null,"profit_index_parameter2":null,"risk_index_parameter2":null,"future_growth_index_parameter":null,"outlook_index_parameter":null,"future_risk_index_parameter":null,"current_index_parameter":null,"future_index_parameter":null,"prediction":null},{"id":"08363d60-8225-4016-a019-48154a1623a3","date":"2015","pkd":"50","pkd_name":"TRANSPORT WODNY","year":"2015","revenue":1870.3000000000002,"net_profit":363.35,"investments":25.76,"firms":46,"profitable_firms":34,"profit_margin":0.19427364593915414,"profitable_share":0.7391304347826086,"bank_debt":293.63,"total_liab":736.47,"leverage_bank_to_rev":0.15699620381756935,"leverage_tot_to_rev":0.39377105277228247,"invest_intensity":0.013773191466609633,"cagr_revenue":0.3939833397733745,"cagr_net_profit":0.70684998395137,"cagr_investments":-0.21126910670657106,"cagr_firms":-0.040043627338746,"profit_margin_std_3y":0.08950420434869319,"size_index":0.1515344389860295,"growth_index":65.00092371347824,"profit_index":86.43966027826433,"risk_index":63.61094225746232,"outlook_index":17.324712338604233,"current_index":56.97373556297154,"future_index":45.51344472672386,"main_index":52.38961922847247,"class1":null,"revenue_parameter":null,"firms_parameter":null,"growth_parameter":null,"cagr_revenue_parameter":null,"cagr_net_profit_parameter":null,"profit_margin_parameter":null,"profitable_share_parameter":null,"leverage_bank_to_rev_parameter":null,"leverage_tot_to_rev_parameter":null,"profit_margin_std_3y_parameter":null,"invest_intensity_parameter":null,"cagr_investments_parameter":null,"size_index_parameter":null,"growth_index_parameter":null,"profit_index_parameter":null,"risk_index_parameter":null,"growth_index_parameter2":null,"profit_index_parameter2":null,"risk_index_parameter2":null,"future_growth_index_parameter":null,"outlook_index_parameter":null,"future_risk_index_parameter":null,"current_index_parameter":null,"future_index_parameter":null,"prediction":null},{"id":"a06074d1-7dd4-450b-9164-1eca4f5414cc","date":"2016","pkd":"50","pkd_name":"TRANSPORT WODNY","year":"2016","revenue":1759.06,"net_profit":415.84999999999997,"investments":86.77,"firms":44,"profitable_firms":30,"profit_margin":0.23640467067638396,"profitable_share":0.6818181818181818,"bank_debt":147.8,"total_liab":799.7099999999999,"leverage_bank_to_rev":0.08402214819278479,"leverage_tot_to_rev":0.45462349209236746,"invest_intensity":0.04932748172319307,"cagr_revenue":0.5663786345907948,"cagr_net_profit":2.6969674218865327,"cagr_investments":0.4157200153314655,"cagr_firms":-0.0772411555836604,"profit_margin_std_3y":0.05198217239189602,"size_index":0.14182509872421747,"growth_index":48.50774268450677,"profit_index":88.76520017262825,"risk_index":79.96037724393442,"outlook_index":40.09226286683354,"current_index":58.33471390720892,"future_index":54.577341125265775,"main_index":56.83176479443166,"class1":null,"revenue_parameter":null,"firms_parameter":null,"growth_parameter":null,"cagr_revenue_parameter":null,"cagr_net_profit_parameter":null,"profit_margin_parameter":null,"profitable_share_parameter":null,"leverage_bank_to_rev_parameter":null,"leverage_tot_to_rev_parameter":null,"profit_margin_std_3y_parameter":null,"invest_intensity_parameter":null,"cagr_investments_parameter":null,"size_index_parameter":null,"growth_index_parameter":null,"profit_index_parameter":null,"risk_index_parameter":null,"growth_index_parameter2":null,"profit_index_parameter2":null,"risk_index_parameter2":null,"future_growth_index_parameter":null,"outlook_index_parameter":null,"future_risk_index_parameter":null,"current_index_parameter":null,"future_index_parameter":null,"prediction":null},{"id":"602b96dc-86ad-43c4-92d7-6d8051c7bcae","date":"2017","pkd":"50","pkd_name":"TRANSPORT WODNY","year":"2017","revenue":2170.14,"net_profit":305.09000000000003,"investments":26.360000000000003,"firms":46,"profitable_firms":30,"profit_margin":0.14058540002027523,"profitable_share":0.6521739130434783,"bank_debt":253.82999999999998,"total_liab":891.78,"leverage_bank_to_rev":0.1169648041140203,"leverage_tot_to_rev":0.41093201360280907,"invest_intensity":0.01214668178089893,"cagr_revenue":0.02789185727360466,"cagr_net_profit":0.047000220354476374,"cagr_investments":0.11046504047168426,"cagr_firms":-0.084758873240947,"profit_margin_std_3y":0.0480256591561978,"size_index":0.15929500638783586,"growth_index":38.10731510370505,"profit_index":72.2353716620801,"risk_index":86.02909346647753,"outlook_index":8.696263158888522,"current_index":53.42625873266711,"future_index":40.71942783461018,"main_index":48.343526373444334,"class1":null,"revenue_parameter":null,"firms_parameter":null,"growth_parameter":null,"cagr_revenue_parameter":null,"cagr_net_profit_parameter":null,"profit_margin_parameter":null,"profitable_share_parameter":null,"leverage_bank_to_rev_parameter":null,"leverage_tot_to_rev_parameter":null,"profit_margin_std_3y_parameter":null,"invest_intensity_parameter":null,"cagr_investments_parameter":null,"size_index_parameter":null,"growth_index_parameter":null,"profit_index_parameter":null,"risk_index_parameter":null,"growth_index_parameter2":null,"profit_index_parameter2":null,"risk_index_parameter2":null,"future_growth_index_parameter":null,"outlook_index_parameter":null,"future_risk_index_parameter":null,"current_index_parameter":null,"future_index_parameter":null,"prediction":null},{"id":"53070594-c94b-43c1-b4e9-f75eb50fb042","date":"2018","pkd":"50","pkd_name":"TRANSPORT WODNY","year":"2018","revenue":2130.84,"net_profit":171.98,"investments":26.68,"firms":46,"profitable_firms":26,"profit_margin":0.08070995475962531,"profitable_share":0.5652173913043478,"bank_debt":252.57,"total_liab":969.99,"leverage_bank_to_rev":0.11853072027932646,"leverage_tot_to_rev":0.4552148448499183,"invest_intensity":0.012520883782921289,"cagr_revenue":0.04443124503064255,"cagr_net_profit":-0.22067682111256792,"cagr_investments":0.011765785274559626,"cagr_firms":0,"profit_margin_std_3y":0.07853581575585952,"size_index":0.1569037492289273,"growth_index":7.661270375028539,"profit_index":70.0291287076772,"risk_index":72.35642822520214,"outlook_index":10.105465824561692,"current_index":41.160908988082866,"future_index":28.04749590989388,"main_index":35.91554375680727,"class1":null,"revenue_parameter":null,"firms_parameter":null,"growth_parameter":null,"cagr_revenue_parameter":null,"cagr_net_profit_parameter":null,"profit_margin_parameter":null,"profitable_share_parameter":null,"leverage_bank_to_rev_parameter":null,"leverage_tot_to_rev_parameter":null,"profit_margin_std_3y_parameter":null,"invest_intensity_parameter":null,"cagr_investments_parameter":null,"size_index_parameter":null,"growth_index_parameter":null,"profit_index_parameter":null,"risk_index_parameter":null,"growth_index_parameter2":null,"profit_index_parameter2":null,"risk_index_parameter2":null,"future_growth_index_parameter":null,"outlook_index_parameter":null,"future_risk_index_parameter":null,"current_index_parameter":null,"future_index_parameter":null,"prediction":null},{"id":"afae506f-a0c4-4a0c-8d5d-85c2a93a3f94","date":"2019","pkd":"50","pkd_name":"TRANSPORT WODNY","year":"2019","revenue":3089.17,"net_profit":216.20999999999998,"investments":3.56,"firms":46,"profitable_firms":28,"profit_margin":0.06998967360164704,"profitable_share":0.6086956521739131,"bank_debt":231.82999999999998,"total_liab":1023.1299999999999,"leverage_bank_to_rev":0.07504604796757705,"leverage_tot_to_rev":0.3311989951993577,"invest_intensity":0.0011524131077279658,"cagr_revenue":0.20648071734877793,"cagr_net_profit":-0.19589451666958946,"cagr_investments":-0.6550997836123662,"cagr_firms":0.014927573906107439,"profit_margin_std_3y":0.03804328666541353,"size_index":0.1800088289397656,"growth_index":47.66553713007153,"profit_index":66.90849744887429,"risk_index":85.32994981841813,"outlook_index":0.6126938810694916,"current_index":54.278495356049845,"future_index":40.14372363697469,"main_index":48.62458666841978,"class1":null,"revenue_parameter":null,"firms_parameter":null,"growth_parameter":null,"cagr_revenue_parameter":null,"cagr_net_profit_parameter":null,"profit_margin_parameter":null,"profitable_share_parameter":null,"leverage_bank_to_rev_parameter":null,"leverage_tot_to_rev_parameter":null,"profit_margin_std_3y_parameter":null,"invest_intensity_parameter":null,"cagr_investments_parameter":null,"size_index_parameter":null,"growth_index_parameter":null,"profit_index_parameter":null,"risk_index_parameter":null,"growth_index_parameter2":null,"profit_index_parameter2":null,"risk_index_parameter2":null,"future_growth_index_parameter":null,"outlook_index_parameter":null,"future_risk_index_parameter":null,"current_index_parameter":null,"future_index_parameter":null,"prediction":null},{"id":"adc0fcb8-1616-432c-991f-52540df394aa","date":"2020","pkd":"50","pkd_name":"TRANSPORT WODNY","year":"2020","revenue":2994.21,"net_profit":118.95,"investments":22.79,"firms":38,"profitable_firms":11,"profit_margin":0.039726672477882315,"profitable_share":0.2894736842105263,"bank_debt":83.1,"total_liab":432.29,"leverage_bank_to_rev":0.027753564379251954,"leverage_tot_to_rev":0.14437531101692935,"invest_intensity":0.007611356584875476,"cagr_revenue":0.11326400720703189,"cagr_net_profit":-0.26945749216712656,"cagr_investments":-0.047350874589960235,"cagr_firms":-0.06169955640427982,"profit_margin_std_3y":0.021254031349793846,"size_index":0.1609693293885881,"growth_index":15.680288958786551,"profit_index":51.05751470509708,"risk_index":95.7439273038795,"outlook_index":20.56738346605831,"current_index":45.439822973012475,"future_index":41.654218265223136,"main_index":43.92558108989674,"class1":null,"revenue_parameter":null,"firms_parameter":null,"growth_parameter":null,"cagr_revenue_parameter":null,"cagr_net_profit_parameter":null,"profit_margin_parameter":null,"profitable_share_parameter":null,"leverage_bank_to_rev_parameter":null,"leverage_tot_to_rev_parameter":null,"profit_margin_std_3y_parameter":null,"invest_intensity_parameter":null,"cagr_investments_parameter":null,"size_index_parameter":null,"growth_index_parameter":null,"profit_index_parameter":null,"risk_index_parameter":null,"growth_index_parameter2":null,"profit_index_parameter2":null,"risk_index_parameter2":null,"future_growth_index_parameter":null,"outlook_index_parameter":null,"future_risk_index_parameter":null,"current_index_parameter":null,"future_index_parameter":null,"prediction":null},{"id":"da8175e7-46ef-46e7-85f9-fa4542e317f2","date":"2021","pkd":"50","pkd_name":"TRANSPORT WODNY","year":"2021","revenue":6792.530000000001,"net_profit":365.08000000000004,"investments":8.41,"firms":34,"profitable_firms":26,"profit_margin":0.053747278260088655,"profitable_share":0.7647058823529411,"bank_debt":118.54,"total_liab":1219.93,"leverage_bank_to_rev":0.017451523953519527,"leverage_tot_to_rev":0.17959876511402967,"invest_intensity":0.0012381248224152118,"cagr_revenue":0.47172581639744404,"cagr_net_profit":0.28519797447808415,"cagr_investments":-0.319434300539993,"cagr_firms":-0.09585025991882279,"profit_margin_std_3y":0.01514508737703693,"size_index":0.2149264331975253,"growth_index":67.81195485527778,"profit_index":60.59334095162819,"risk_index":97.55626123656609,"outlook_index":0,"current_index":61.411187609335826,"future_index":49.61046482755316,"main_index":56.69089849662276,"class1":null,"revenue_parameter":null,"firms_parameter":null,"growth_parameter":null,"cagr_revenue_parameter":null,"cagr_net_profit_parameter":null,"profit_margin_parameter":null,"profitable_share_parameter":null,"leverage_bank_to_rev_parameter":null,"leverage_tot_to_rev_parameter":null,"profit_margin_std_3y_parameter":null,"invest_intensity_parameter":null,"cagr_investments_parameter":null,"size_index_parameter":null,"growth_index_parameter":null,"profit_index_parameter":null,"risk_index_parameter":null,"growth_index_parameter2":null,"profit_index_parameter2":null,"risk_index_parameter2":null,"future_growth_index_parameter":null,"outlook_index_parameter":null,"future_risk_index_parameter":null,"current_index_parameter":null,"future_index_parameter":null,"prediction":null},{"id":"4431171d-9ce0-469d-bfb2-d5fbc02233a5","date":"2022","pkd":"50","pkd_name":"TRANSPORT WODNY","year":"2022","revenue":9480.18,"net_profit":670.3,"investments":98.86,"firms":38,"profitable_firms":27,"profit_margin":0.07070540854709509,"profitable_share":0.7105263157894737,"bank_debt":166.89,"total_liab":1019.13,"leverage_bank_to_rev":0.017604096124757124,"leverage_tot_to_rev":0.1075011233963912,"invest_intensity":0.010428072040826228,"cagr_revenue":0.4531984464912797,"cagr_net_profit":0.45813526736441834,"cagr_investments":2.0282393792095563,"cagr_firms":-0.06169955640427982,"profit_margin_std_3y":0.015512562961339151,"size_index":0.2386850151579833,"growth_index":64.08181851918009,"profit_index":69.39339588685559,"risk_index":97.53550830826052,"outlook_index":50.47840559982536,"current_index":62.67719309701867,"future_index":68.67656028816232,"main_index":65.07693997347613,"class1":null,"revenue_parameter":null,"firms_parameter":null,"growth_parameter":null,"cagr_revenue_parameter":null,"cagr_net_profit_parameter":null,"profit_margin_parameter":null,"profitable_share_parameter":null,"leverage_bank_to_rev_parameter":null,"leverage_tot_to_rev_parameter":null,"profit_margin_std_3y_parameter":null,"invest_intensity_parameter":null,"cagr_investments_parameter":null,"size_index_parameter":null,"growth_index_parameter":null,"profit_index_parameter":null,"risk_index_parameter":null,"growth_index_parameter2":null,"profit_index_parameter2":null,"risk_index_parameter2":null,"future_growth_index_parameter":null,"outlook_index_parameter":null,"future_risk_index_parameter":null,"current_index_parameter":null,"future_index_parameter":null,"prediction":null},{"id":"57c2d2ed-6295-462b-acdf-3b663594027a","date":"2023","pkd":"50","pkd_name":"TRANSPORT WODNY","year":"2023","revenue":4832.77,"net_profit":413.09000000000003,"investments":449.65,"firms":44,"profitable_firms":33,"profit_margin":0.08547685902701763,"profitable_share":0.75,"bank_debt":682.97,"total_liab":1286.45,"leverage_bank_to_rev":0.14132060909168034,"leverage_tot_to_rev":0.2661930942296033,"invest_intensity":0.0930418786741351,"cagr_revenue":0.17301785687495586,"cagr_net_profit":0.5143516850543253,"cagr_investments":1.7021539647867727,"cagr_firms":0.050081546755695205,"profit_margin_std_3y":0.015877343542277246,"size_index":0.18527010424486273,"growth_index":45.49467278303544,"profit_index":68.22554457565018,"risk_index":94.74864694305603,"outlook_index":54.250382930870906,"current_index":56.89170244343718,"future_index":63.77314909017581,"main_index":59.64428110213263,"class1":null,"revenue_parameter":null,"firms_parameter":null,"growth_parameter":null,"cagr_revenue_parameter":null,"cagr_net_profit_parameter":null,"profit_margin_parameter":null,"profitable_share_parameter":null,"leverage_bank_to_rev_parameter":null,"leverage_tot_to_rev_parameter":null,"profit_margin_std_3y_parameter":null,"invest_intensity_parameter":null,"cagr_investments_parameter":null,"size_index_parameter":null,"growth_index_parameter":null,"profit_index_parameter":null,"risk_index_parameter":null,"growth_index_parameter2":null,"profit_index_parameter2":null,"risk_index_parameter2":null,"future_growth_index_parameter":null,"outlook_index_parameter":null,"future_risk_index_parameter":null,"current_index_parameter":null,"future_index_parameter":null,"prediction":null},{"id":"8b3a6d5f-242c-4a15-acf2-cf2c50e5ca6f","date":"2024","pkd":"50","pkd_name":"TRANSPORT WODNY","year":"2024","revenue":5203.32,"net_profit":187.39,"investments":129.64,"firms":50,"profitable_firms":38,"profit_margin":0.03601354519806585,"profitable_share":0.76,"bank_debt":592.1,"total_liab":1281.0700000000002,"leverage_bank_to_rev":0.11379273233243392,"leverage_tot_to_rev":0.24620242460582864,"invest_intensity":0.024914862049614475,"cagr_revenue":-0.0850100510455718,"cagr_net_profit":-0.19933141334041093,"cagr_investments":1.4887484860935722,"cagr_firms":0.1371830097629767,"profit_margin_std_3y":0.025391404539233,"size_index":0.2061621433542637,"growth_index":59.01347973479707,"profit_index":76.27004991715873,"risk_index":95.46521822496572,"outlook_index":51.07699469862981,"current_index":62.50168030914952,"future_index":66.77440726738077,"main_index":64.21077109244202,"class1":null,"revenue_parameter":null,"firms_parameter":null,"growth_parameter":null,"cagr_revenue_parameter":null,"cagr_net_profit_parameter":null,"profit_margin_parameter":null,"profitable_share_parameter":null,"leverage_bank_to_rev_parameter":null,"leverage_tot_to_rev_parameter":null,"profit_margin_std_3y_parameter":null,"invest_intensity_parameter":null,"cagr_investments_parameter":null,"size_index_parameter":null,"growth_index_parameter":null,"profit_index_parameter":null,"risk_index_parameter":null,"growth_index_parameter2":null,"profit_index_parameter2":null,"risk_index_parameter2":null,"future_growth_index_parameter":null,"outlook_index_parameter":null,"future_risk_index_parameter":null,"current_index_parameter":null,"future_index_parameter":null,"prediction":null},{"id":"68258fed-95ea-47bc-bcbd-4bf9ecbc6f1e","date":"2025","pkd":"50","pkd_name":"","year":"2025","revenue":null,"net_profit":null,"investments":null,"firms":null,"profitable_firms":null,"profit_margin":null,"profitable_share":null,"bank_debt":null,"total_liab":null,"leverage_bank_to_rev":null,"leverage_tot_to_rev":null,"invest_intensity":null,"cagr_revenue":null,"cagr_net_profit":null,"cagr_investments":null,"cagr_firms":null,"profit_margin_std_3y":null,"size_index":null,"growth_index":null,"profit_index":null,"risk_index":null,"outlook_index":null,"current_index":null,"future_index":null,"main_index":58.93882350787362,"class1":null,"revenue_parameter":null,"firms_parameter":null,"growth_parameter":null,"cagr_revenue_parameter":null,"cagr_net_profit_parameter":null,"profit_margin_parameter":null,"profitable_share_parameter":null,"leverage_bank_to_rev_parameter":null,"leverage_tot_to_rev_parameter":null,"profit_margin_std_3y_parameter":null,"invest_intensity_parameter":null,"cagr_investments_parameter":null,"size_index_parameter":null,"growth_index_parameter":null,"profit_index_parameter":null,"risk_index_parameter":null,"growth_index_parameter2":null,"profit_index_parameter2":null,"risk_index_parameter2":null,"future_growth_index_parameter":null,"outlook_index_parameter":null,"future_risk_index_parameter":null,"current_index_parameter":null,"future_index_parameter":null,"prediction":null},{"id":"d6e99024-da98-4adf-b873-0df13224b2d7","date":"2026","pkd":"50","pkd_name":"","year":"2026","revenue":null,"net_profit":null,"investments":null,"firms":null,"profitable_firms":null,"profit_margin":null,"profitable_share":null,"bank_debt":null,"total_liab":null,"leverage_bank_to_rev":null,"leverage_tot_to_rev":null,"invest_intensity":null,"cagr_revenue":null,"cagr_net_profit":null,"cagr_investments":null,"cagr_firms":null,"profit_margin_std_3y":null,"size_index":null,"growth_index":null,"profit_index":null,"risk_index":null,"outlook_index":null,"current_index":null,"future_index":null,"main_index":60.475275061733555,"class1":null,"revenue_parameter":null,"firms_parameter":null,"growth_parameter":null,"cagr_revenue_parameter":null,"cagr_net_profit_parameter":null,"profit_margin_parameter":null,"profitable_share_parameter":null,"leverage_bank_to_rev_parameter":null,"leverage_tot_to_rev_parameter":null,"profit_margin_std_3y_parameter":null,"invest_intensity_parameter":null,"cagr_investments_parameter":null,"size_index_parameter":null,"growth_index_parameter":null,"profit_index_parameter":null,"risk_index_parameter":null,"growth_index_parameter2":null,"profit_index_parameter2":null,"risk_index_parameter2":null,"future_growth_index_parameter":null,"outlook_index_parameter":null,"future_risk_index_parameter":null,"current_index_parameter":null,"future_index_parameter":null,"prediction":null},{"id":"84266f17-957a-4dbb-a011-30515376ceaf","date":"2027","pkd":"50","pkd_name":"","year":"2027","revenue":null,"net_profit":null,"investments":null,"firms":null,"profitable_firms":null,"profit_margin":null,"profitable_share":null,"bank_debt":null,"total_liab":null,"leverage_bank_to_rev":null,"leverage_tot_to_rev":null,"invest_intensity":null,"cagr_revenue":null,"cagr_net_profit":null,"cagr_investments":null,"cagr_firms":null,"profit_margin_std_3y":null,"size_index":null,"growth_index":null,"profit_index":null,"risk_index":null,"outlook_index":null,"current_index":null,"future_index":null,"main_index":62.01172661559349,"class1":null,"revenue_parameter":null,"firms_parameter":null,"growth_parameter":null,"cagr_revenue_parameter":null,"cagr_net_profit_parameter":null,"profit_margin_parameter":null,"profitable_share_parameter":null,"leverage_bank_to_rev_parameter":null,"leverage_tot_to_rev_parameter":null,"profit_margin_std_3y_parameter":null,"invest_intensity_parameter":null,"cagr_investments_parameter":null,"size_index_parameter":null,"growth_index_parameter":null,"profit_index_parameter":null,"risk_index_parameter":null,"growth_index_parameter2":null,"profit_index_parameter2":null,"risk_index_parameter2":null,"future_growth_index_parameter":null,"outlook_index_parameter":null,"future_risk_index_parameter":null,"current_index_parameter":null,"future_index_parameter":null,"prediction":null}]