[{"id":"1bd5e755-bf7e-4501-a7b4-e79f479e82b5","date":"2005","pkd":"70","pkd_name":"DZIAŁALNOŚĆ FIRM CENTRALNYCH (HEAD OFFICES); DORADZTWO ZWIĄZANE Z ZARZĄDZANIEM","year":"2005","revenue":5574.48,"net_profit":751.02,"investments":152.91,"firms":541,"profitable_firms":242,"profit_margin":0.1347246738709261,"profitable_share":0.44731977818853974,"bank_debt":726.1600000000001,"total_liab":5387.78,"leverage_bank_to_rev":0.13026506508230368,"leverage_tot_to_rev":0.9665080868529442,"invest_intensity":0.027430361217548545,"cagr_revenue":null,"cagr_net_profit":null,"cagr_investments":null,"cagr_firms":null,"profit_margin_std_3y":null,"size_index":1.5355738171770794,"growth_index":null,"profit_index":73.52448534016239,"risk_index":54.04971957843311,"outlook_index":1.1630220556306579,"current_index":34.90315197200594,"future_index":16.680124695782194,"main_index":27.613941061516442,"class1":null,"revenue_parameter":null,"firms_parameter":null,"growth_parameter":null,"cagr_revenue_parameter":null,"cagr_net_profit_parameter":null,"profit_margin_parameter":null,"profitable_share_parameter":null,"leverage_bank_to_rev_parameter":null,"leverage_tot_to_rev_parameter":null,"profit_margin_std_3y_parameter":null,"invest_intensity_parameter":null,"cagr_investments_parameter":null,"size_index_parameter":null,"growth_index_parameter":null,"profit_index_parameter":null,"risk_index_parameter":null,"growth_index_parameter2":null,"profit_index_parameter2":null,"risk_index_parameter2":null,"future_growth_index_parameter":null,"outlook_index_parameter":null,"future_risk_index_parameter":null,"current_index_parameter":null,"future_index_parameter":null,"prediction":null},{"id":"3872d626-6b55-49f8-a554-51a96a2b5fdd","date":"2006","pkd":"70","pkd_name":"DZIAŁALNOŚĆ FIRM CENTRALNYCH (HEAD OFFICES); DORADZTWO ZWIĄZANE Z ZARZĄDZANIEM","year":"2006","revenue":3004.89,"net_profit":354.73,"investments":115.19,"firms":597,"profitable_firms":144,"profit_margin":0.11805091034946372,"profitable_share":0.24120603015075376,"bank_debt":275.54,"total_liab":2724.3,"leverage_bank_to_rev":0.0916972002302913,"leverage_tot_to_rev":0.9066222058045387,"invest_intensity":0.038334181950088024,"cagr_revenue":null,"cagr_net_profit":null,"cagr_investments":null,"cagr_firms":null,"profit_margin_std_3y":0.011790131253926939,"size_index":1.5512718844700268,"growth_index":null,"profit_index":37.90059932673191,"risk_index":88.05342286709067,"outlook_index":1.5242117154289803,"current_index":36.20143106870418,"future_index":27.025711546298794,"main_index":32.531143259742024,"class1":null,"revenue_parameter":null,"firms_parameter":null,"growth_parameter":null,"cagr_revenue_parameter":null,"cagr_net_profit_parameter":null,"profit_margin_parameter":null,"profitable_share_parameter":null,"leverage_bank_to_rev_parameter":null,"leverage_tot_to_rev_parameter":null,"profit_margin_std_3y_parameter":null,"invest_intensity_parameter":null,"cagr_investments_parameter":null,"size_index_parameter":null,"growth_index_parameter":null,"profit_index_parameter":null,"risk_index_parameter":null,"growth_index_parameter2":null,"profit_index_parameter2":null,"risk_index_parameter2":null,"future_growth_index_parameter":null,"outlook_index_parameter":null,"future_risk_index_parameter":null,"current_index_parameter":null,"future_index_parameter":null,"prediction":null},{"id":"142a9f08-b4c3-468a-a54f-fd6a7a8d8436","date":"2007","pkd":"70","pkd_name":"DZIAŁALNOŚĆ FIRM CENTRALNYCH (HEAD OFFICES); DORADZTWO ZWIĄZANE Z ZARZĄDZANIEM","year":"2007","revenue":4290.35,"net_profit":629.83,"investments":549.35,"firms":660,"profitable_firms":172,"profit_margin":0.14680154299765752,"profitable_share":0.2606060606060606,"bank_debt":263.54,"total_liab":3301.8399999999997,"leverage_bank_to_rev":0.06142622396774156,"leverage_tot_to_rev":0.7695968860349387,"invest_intensity":0.12804316664141618,"cagr_revenue":null,"cagr_net_profit":null,"cagr_investments":null,"cagr_firms":null,"profit_margin_std_3y":0.01443643559161584,"size_index":1.7307728050472349,"growth_index":null,"profit_index":56.28302970015982,"risk_index":90.78021775719077,"outlook_index":4.704576177896915,"current_index":41.65097731320663,"future_index":29.115895798315997,"main_index":36.63694470725038,"class1":null,"revenue_parameter":null,"firms_parameter":null,"growth_parameter":null,"cagr_revenue_parameter":null,"cagr_net_profit_parameter":null,"profit_margin_parameter":null,"profitable_share_parameter":null,"leverage_bank_to_rev_parameter":null,"leverage_tot_to_rev_parameter":null,"profit_margin_std_3y_parameter":null,"invest_intensity_parameter":null,"cagr_investments_parameter":null,"size_index_parameter":null,"growth_index_parameter":null,"profit_index_parameter":null,"risk_index_parameter":null,"growth_index_parameter2":null,"profit_index_parameter2":null,"risk_index_parameter2":null,"future_growth_index_parameter":null,"outlook_index_parameter":null,"future_risk_index_parameter":null,"current_index_parameter":null,"future_index_parameter":null,"prediction":null},{"id":"1463d9c7-9af1-462f-a3b9-abb7075e30fe","date":"2008","pkd":"70","pkd_name":"DZIAŁALNOŚĆ FIRM CENTRALNYCH (HEAD OFFICES); DORADZTWO ZWIĄZANE Z ZARZĄDZANIEM","year":"2008","revenue":8229.11,"net_profit":563.95,"investments":370.4,"firms":947,"profitable_firms":215,"profit_margin":0.06853110482178511,"profitable_share":0.22703273495248152,"bank_debt":1369.9299999999998,"total_liab":5368.639999999999,"leverage_bank_to_rev":0.16647365267932981,"leverage_tot_to_rev":0.6523961886522357,"invest_intensity":0.04501094286016349,"cagr_revenue":0.1386305588535881,"cagr_net_profit":-0.09107154550388341,"cagr_investments":0.3430072688409356,"cagr_firms":0.205177193620647,"profit_margin_std_3y":0.03959181630382211,"size_index":2.2704935150094414,"growth_index":75.21453624838709,"profit_index":46.756643629717736,"risk_index":88.62935139562676,"outlook_index":33.37028749807787,"current_index":57.535699091216124,"future_index":62.5012812924353,"main_index":59.52193197170379,"class1":null,"revenue_parameter":null,"firms_parameter":null,"growth_parameter":null,"cagr_revenue_parameter":null,"cagr_net_profit_parameter":null,"profit_margin_parameter":null,"profitable_share_parameter":null,"leverage_bank_to_rev_parameter":null,"leverage_tot_to_rev_parameter":null,"profit_margin_std_3y_parameter":null,"invest_intensity_parameter":null,"cagr_investments_parameter":null,"size_index_parameter":null,"growth_index_parameter":null,"profit_index_parameter":null,"risk_index_parameter":null,"growth_index_parameter2":null,"profit_index_parameter2":null,"risk_index_parameter2":null,"future_growth_index_parameter":null,"outlook_index_parameter":null,"future_risk_index_parameter":null,"current_index_parameter":null,"future_index_parameter":null,"prediction":null},{"id":"e2232335-6533-4f97-9e24-188b3d77498e","date":"2009","pkd":"70","pkd_name":"DZIAŁALNOŚĆ FIRM CENTRALNYCH (HEAD OFFICES); DORADZTWO ZWIĄZANE Z ZARZĄDZANIEM","year":"2009","revenue":22055.690000000002,"net_profit":1279.51,"investments":1131.99,"firms":1040,"profitable_firms":472,"profit_margin":0.05801269422992433,"profitable_share":0.45384615384615384,"bank_debt":4341.8099999999995,"total_liab":18752.42,"leverage_bank_to_rev":0.19685668414817215,"leverage_tot_to_rev":0.8502304847411256,"invest_intensity":0.05132417076953838,"cagr_revenue":0.9434081671950456,"cagr_net_profit":0.5336111422345482,"cagr_investments":1.1419497134180325,"cagr_firms":0.20324205502245984,"profit_margin_std_3y":0.04851178227867505,"size_index":3.039935309835342,"growth_index":74.6451133175463,"profit_index":37.00845448591795,"risk_index":86.01122271471817,"outlook_index":53.450319396211746,"current_index":54.324745827248584,"future_index":69.57702856816404,"main_index":60.42565892361476,"class1":null,"revenue_parameter":null,"firms_parameter":null,"growth_parameter":null,"cagr_revenue_parameter":null,"cagr_net_profit_parameter":null,"profit_margin_parameter":null,"profitable_share_parameter":null,"leverage_bank_to_rev_parameter":null,"leverage_tot_to_rev_parameter":null,"profit_margin_std_3y_parameter":null,"invest_intensity_parameter":null,"cagr_investments_parameter":null,"size_index_parameter":null,"growth_index_parameter":null,"profit_index_parameter":null,"risk_index_parameter":null,"growth_index_parameter2":null,"profit_index_parameter2":null,"risk_index_parameter2":null,"future_growth_index_parameter":null,"outlook_index_parameter":null,"future_risk_index_parameter":null,"current_index_parameter":null,"future_index_parameter":null,"prediction":null},{"id":"3666c223-cb26-446e-9173-4da49ccd7b43","date":"2010","pkd":"70","pkd_name":"DZIAŁALNOŚĆ FIRM CENTRALNYCH (HEAD OFFICES); DORADZTWO ZWIĄZANE Z ZARZĄDZANIEM","year":"2010","revenue":38345.33,"net_profit":2526.7200000000003,"investments":862.14,"firms":1071,"profitable_firms":767,"profit_margin":0.06589381288412435,"profitable_share":0.7161531279178338,"bank_debt":8735.3,"total_liab":36887.590000000004,"leverage_bank_to_rev":0.22780609790031794,"leverage_tot_to_rev":0.9619838973872438,"invest_intensity":0.02248357231506418,"cagr_revenue":1.0752635220296338,"cagr_net_profit":0.5889537573613983,"cagr_investments":0.16209836127831645,"cagr_firms":0.17511899147492738,"profit_margin_std_3y":0.005472724814706089,"size_index":3.6293679362414277,"growth_index":98.72489886027387,"profit_index":62.693412179212736,"risk_index":85.3543686853696,"outlook_index":30.550820208918946,"current_index":66.68676195273082,"future_index":67.44410834726061,"main_index":66.98970051054273,"class1":null,"revenue_parameter":null,"firms_parameter":null,"growth_parameter":null,"cagr_revenue_parameter":null,"cagr_net_profit_parameter":null,"profit_margin_parameter":null,"profitable_share_parameter":null,"leverage_bank_to_rev_parameter":null,"leverage_tot_to_rev_parameter":null,"profit_margin_std_3y_parameter":null,"invest_intensity_parameter":null,"cagr_investments_parameter":null,"size_index_parameter":null,"growth_index_parameter":null,"profit_index_parameter":null,"risk_index_parameter":null,"growth_index_parameter2":null,"profit_index_parameter2":null,"risk_index_parameter2":null,"future_growth_index_parameter":null,"outlook_index_parameter":null,"future_risk_index_parameter":null,"current_index_parameter":null,"future_index_parameter":null,"prediction":null},{"id":"a0124d53-bcc6-4788-85a0-e7f516d8a2ed","date":"2011","pkd":"70","pkd_name":"DZIAŁALNOŚĆ FIRM CENTRALNYCH (HEAD OFFICES); DORADZTWO ZWIĄZANE Z ZARZĄDZANIEM","year":"2011","revenue":13863.64,"net_profit":-7921.929999999999,"investments":849.86,"firms":1172,"profitable_firms":541,"profit_margin":-0.5714177517592782,"profitable_share":0.4616040955631399,"bank_debt":14483.45,"total_liab":27360.370000000003,"leverage_bank_to_rev":1.044707594830795,"leverage_tot_to_rev":1.9735343675975432,"invest_intensity":0.06130136097013483,"cagr_revenue":0.18989361727994614,"cagr_net_profit":-5.0157401660903735,"cagr_investments":0.31894130846975477,"cagr_firms":0.0736413040635393,"profit_margin_std_3y":0.36569815166738034,"size_index":2.964274505447008,"growth_index":34.569756273882774,"profit_index":26.234765638839356,"risk_index":43.742137877139,"outlook_index":23.755491324030686,"current_index":28.916626742411633,"future_index":32.99576477491881,"main_index":30.548281955414502,"class1":null,"revenue_parameter":null,"firms_parameter":null,"growth_parameter":null,"cagr_revenue_parameter":null,"cagr_net_profit_parameter":null,"profit_margin_parameter":null,"profitable_share_parameter":null,"leverage_bank_to_rev_parameter":null,"leverage_tot_to_rev_parameter":null,"profit_margin_std_3y_parameter":null,"invest_intensity_parameter":null,"cagr_investments_parameter":null,"size_index_parameter":null,"growth_index_parameter":null,"profit_index_parameter":null,"risk_index_parameter":null,"growth_index_parameter2":null,"profit_index_parameter2":null,"risk_index_parameter2":null,"future_growth_index_parameter":null,"outlook_index_parameter":null,"future_risk_index_parameter":null,"current_index_parameter":null,"future_index_parameter":null,"prediction":null},{"id":"ad9017ce-867c-4899-b853-66d63e674041","date":"2012","pkd":"70","pkd_name":"DZIAŁALNOŚĆ FIRM CENTRALNYCH (HEAD OFFICES); DORADZTWO ZWIĄZANE Z ZARZĄDZANIEM","year":"2012","revenue":30893.010000000002,"net_profit":11393.69,"investments":2164.37,"firms":1223,"profitable_firms":914,"profit_margin":0.3688112618356062,"profitable_share":0.7473426001635323,"bank_debt":16038.84,"total_liab":34307,"leverage_bank_to_rev":0.519173754839687,"leverage_tot_to_rev":1.1105101121580576,"invest_intensity":0.07006018513573134,"cagr_revenue":0.11887059074761108,"cagr_net_profit":1.07271809178165,"cagr_investments":0.2411653376737266,"cagr_firms":0.05551491032103728,"profit_margin_std_3y":0.4799228426377697,"size_index":3.4913391127257425,"growth_index":24.214036627292415,"profit_index":91.51903334241845,"risk_index":54.030387440875955,"outlook_index":7.498819444514557,"current_index":45.84065154723565,"future_index":26.472854998256334,"main_index":38.09353292764392,"class1":null,"revenue_parameter":null,"firms_parameter":null,"growth_parameter":null,"cagr_revenue_parameter":null,"cagr_net_profit_parameter":null,"profit_margin_parameter":null,"profitable_share_parameter":null,"leverage_bank_to_rev_parameter":null,"leverage_tot_to_rev_parameter":null,"profit_margin_std_3y_parameter":null,"invest_intensity_parameter":null,"cagr_investments_parameter":null,"size_index_parameter":null,"growth_index_parameter":null,"profit_index_parameter":null,"risk_index_parameter":null,"growth_index_parameter2":null,"profit_index_parameter2":null,"risk_index_parameter2":null,"future_growth_index_parameter":null,"outlook_index_parameter":null,"future_risk_index_parameter":null,"current_index_parameter":null,"future_index_parameter":null,"prediction":null},{"id":"996119e3-4d4b-4e10-9751-54105ec4d157","date":"2013","pkd":"70","pkd_name":"DZIAŁALNOŚĆ FIRM CENTRALNYCH (HEAD OFFICES); DORADZTWO ZWIĄZANE Z ZARZĄDZANIEM","year":"2013","revenue":34687.1,"net_profit":1856.4,"investments":2142.26,"firms":1338,"profitable_firms":921,"profit_margin":0.05351845498758905,"profitable_share":0.6883408071748879,"bank_debt":24480.62,"total_liab":44531.020000000004,"leverage_bank_to_rev":0.7057557420481966,"leverage_tot_to_rev":1.2837919572405883,"invest_intensity":0.061759559029149175,"cagr_revenue":-0.03286929685028739,"cagr_net_profit":-0.09765735948649035,"cagr_investments":0.35445566677990503,"cagr_firms":0.07701614640367604,"profit_margin_std_3y":0.47853690463029663,"size_index":3.728606921076273,"growth_index":20.521659909642704,"profit_index":61.626641963605124,"risk_index":50.440360935618855,"outlook_index":7.3911740648076165,"current_index":36.41490513321287,"future_index":24.245075879501513,"main_index":31.546973431728325,"class1":null,"revenue_parameter":null,"firms_parameter":null,"growth_parameter":null,"cagr_revenue_parameter":null,"cagr_net_profit_parameter":null,"profit_margin_parameter":null,"profitable_share_parameter":null,"leverage_bank_to_rev_parameter":null,"leverage_tot_to_rev_parameter":null,"profit_margin_std_3y_parameter":null,"invest_intensity_parameter":null,"cagr_investments_parameter":null,"size_index_parameter":null,"growth_index_parameter":null,"profit_index_parameter":null,"risk_index_parameter":null,"growth_index_parameter2":null,"profit_index_parameter2":null,"risk_index_parameter2":null,"future_growth_index_parameter":null,"outlook_index_parameter":null,"future_risk_index_parameter":null,"current_index_parameter":null,"future_index_parameter":null,"prediction":null},{"id":"c28e0ede-53b1-423a-9b93-d11dd6ceb954","date":"2014","pkd":"70","pkd_name":"DZIAŁALNOŚĆ FIRM CENTRALNYCH (HEAD OFFICES); DORADZTWO ZWIĄZANE Z ZARZĄDZANIEM","year":"2014","revenue":41236.95,"net_profit":5807.48,"investments":2737.4,"firms":1320,"profitable_firms":921,"profit_margin":0.14083194804659413,"profitable_share":0.6977272727272728,"bank_debt":23622.21,"total_liab":47804.259999999995,"leverage_bank_to_rev":0.5728408623819172,"leverage_tot_to_rev":1.159257898559423,"invest_intensity":0.06638221303951918,"cagr_revenue":0.4381463650032238,"cagr_net_profit":0.5776963441989516,"cagr_investments":0.4768292701910386,"cagr_firms":0.040436165510463695,"profit_margin_std_3y":0.16279218226314124,"size_index":3.8633008714339514,"growth_index":21.021109858279054,"profit_index":89.76557533375716,"risk_index":53.348852937010214,"outlook_index":24.68544319252057,"current_index":44.473987353398904,"future_index":32.18516611559501,"main_index":39.55845885827735,"class1":null,"revenue_parameter":null,"firms_parameter":null,"growth_parameter":null,"cagr_revenue_parameter":null,"cagr_net_profit_parameter":null,"profit_margin_parameter":null,"profitable_share_parameter":null,"leverage_bank_to_rev_parameter":null,"leverage_tot_to_rev_parameter":null,"profit_margin_std_3y_parameter":null,"invest_intensity_parameter":null,"cagr_investments_parameter":null,"size_index_parameter":null,"growth_index_parameter":null,"profit_index_parameter":null,"risk_index_parameter":null,"growth_index_parameter2":null,"profit_index_parameter2":null,"risk_index_parameter2":null,"future_growth_index_parameter":null,"outlook_index_parameter":null,"future_risk_index_parameter":null,"current_index_parameter":null,"future_index_parameter":null,"prediction":null},{"id":"427e6148-9c79-4f25-8dc7-0786b5b3679e","date":"2015","pkd":"70","pkd_name":"DZIAŁALNOŚĆ FIRM CENTRALNYCH (HEAD OFFICES); DORADZTWO ZWIĄZANE Z ZARZĄDZANIEM","year":"2015","revenue":24994.28,"net_profit":1556.94,"investments":1636.22,"firms":1349,"profitable_firms":624,"profit_margin":0.062291852375823596,"profitable_share":0.4625648628613788,"bank_debt":13364.97,"total_liab":28823.04,"leverage_bank_to_rev":0.5347211441977925,"leverage_tot_to_rev":1.1531854488306925,"invest_intensity":0.06546377811243213,"cagr_revenue":-0.06819121222528779,"cagr_net_profit":-0.48492655610125224,"cagr_investments":-0.08903142209591652,"cagr_firms":0.03322561465489615,"profit_margin_std_3y":0.048078347863791726,"size_index":3.59710799542654,"growth_index":22.80323051640898,"profit_index":54.97216704003442,"risk_index":71.61633975293951,"outlook_index":25.763649398950918,"current_index":41.64817291407802,"future_index":38.63133084038492,"main_index":40.44143608460078,"class1":null,"revenue_parameter":null,"firms_parameter":null,"growth_parameter":null,"cagr_revenue_parameter":null,"cagr_net_profit_parameter":null,"profit_margin_parameter":null,"profitable_share_parameter":null,"leverage_bank_to_rev_parameter":null,"leverage_tot_to_rev_parameter":null,"profit_margin_std_3y_parameter":null,"invest_intensity_parameter":null,"cagr_investments_parameter":null,"size_index_parameter":null,"growth_index_parameter":null,"profit_index_parameter":null,"risk_index_parameter":null,"growth_index_parameter2":null,"profit_index_parameter2":null,"risk_index_parameter2":null,"future_growth_index_parameter":null,"outlook_index_parameter":null,"future_risk_index_parameter":null,"current_index_parameter":null,"future_index_parameter":null,"prediction":null},{"id":"cb6b979b-4347-4ac3-a77b-41e16cf993fe","date":"2016","pkd":"70","pkd_name":"DZIAŁALNOŚĆ FIRM CENTRALNYCH (HEAD OFFICES); DORADZTWO ZWIĄZANE Z ZARZĄDZANIEM","year":"2016","revenue":47305.270000000004,"net_profit":2565.07,"investments":1518.29,"firms":1589,"profitable_firms":1133,"profit_margin":0.05422376830319328,"profitable_share":0.7130270610446822,"bank_debt":20438.760000000002,"total_liab":50727.009999999995,"leverage_bank_to_rev":0.4320609521941213,"leverage_tot_to_rev":1.0723331671080196,"invest_intensity":0.03209557835733735,"cagr_revenue":0.10895479836537048,"cagr_net_profit":0.11380514717630108,"cagr_investments":-0.10841890545343869,"cagr_firms":0.05898366540070743,"profit_margin_std_3y":0.047844570237109196,"size_index":4.671297145111549,"growth_index":23.21933986248676,"profit_index":63.629170636545375,"risk_index":74.86516928587955,"outlook_index":20.569565698561284,"current_index":45.10593783954421,"future_index":37.653179023934406,"main_index":42.12483431330029,"class1":null,"revenue_parameter":null,"firms_parameter":null,"growth_parameter":null,"cagr_revenue_parameter":null,"cagr_net_profit_parameter":null,"profit_margin_parameter":null,"profitable_share_parameter":null,"leverage_bank_to_rev_parameter":null,"leverage_tot_to_rev_parameter":null,"profit_margin_std_3y_parameter":null,"invest_intensity_parameter":null,"cagr_investments_parameter":null,"size_index_parameter":null,"growth_index_parameter":null,"profit_index_parameter":null,"risk_index_parameter":null,"growth_index_parameter2":null,"profit_index_parameter2":null,"risk_index_parameter2":null,"future_growth_index_parameter":null,"outlook_index_parameter":null,"future_risk_index_parameter":null,"current_index_parameter":null,"future_index_parameter":null,"prediction":null},{"id":"cc7c1e40-8ca6-42f2-88ac-5ad4ef4229db","date":"2017","pkd":"70","pkd_name":"DZIAŁALNOŚĆ FIRM CENTRALNYCH (HEAD OFFICES); DORADZTWO ZWIĄZANE Z ZARZĄDZANIEM","year":"2017","revenue":40093.16,"net_profit":9785.89,"investments":1292.44,"firms":1617,"profitable_firms":1209,"profit_margin":0.2440787904969326,"profitable_share":0.7476808905380334,"bank_debt":26473.28,"total_liab":56473.36,"leverage_bank_to_rev":0.6602941748667353,"leverage_tot_to_rev":1.4085534789475311,"invest_intensity":0.03223592253641269,"cagr_revenue":-0.009332497030636322,"cagr_net_profit":0.1899741729375124,"cagr_investments":-0.22132294819431453,"cagr_firms":0.06998748056507953,"profit_margin_std_3y":0.10735960933876715,"size_index":4.667833546548749,"growth_index":38.699283438271834,"profit_index":91.2183055040198,"risk_index":62.774486116713646,"outlook_index":3.212301920221925,"current_index":52.24530977989674,"future_index":31.727051634584413,"main_index":44.03800652177181,"class1":null,"revenue_parameter":null,"firms_parameter":null,"growth_parameter":null,"cagr_revenue_parameter":null,"cagr_net_profit_parameter":null,"profit_margin_parameter":null,"profitable_share_parameter":null,"leverage_bank_to_rev_parameter":null,"leverage_tot_to_rev_parameter":null,"profit_margin_std_3y_parameter":null,"invest_intensity_parameter":null,"cagr_investments_parameter":null,"size_index_parameter":null,"growth_index_parameter":null,"profit_index_parameter":null,"risk_index_parameter":null,"growth_index_parameter2":null,"profit_index_parameter2":null,"risk_index_parameter2":null,"future_growth_index_parameter":null,"outlook_index_parameter":null,"future_risk_index_parameter":null,"current_index_parameter":null,"future_index_parameter":null,"prediction":null},{"id":"6ea0712f-f1a6-4b15-9b72-d8deb3cfd1ae","date":"2018","pkd":"70","pkd_name":"DZIAŁALNOŚĆ FIRM CENTRALNYCH (HEAD OFFICES); DORADZTWO ZWIĄZANE Z ZARZĄDZANIEM","year":"2018","revenue":48191.5,"net_profit":3712.41,"investments":1536.08,"firms":1701,"profitable_firms":1359,"profit_margin":0.07703453928597366,"profitable_share":0.798941798941799,"bank_debt":33250.69,"total_liab":63927.63,"leverage_bank_to_rev":0.6899700154591578,"leverage_tot_to_rev":1.3265333098160463,"invest_intensity":0.0318745006899557,"cagr_revenue":0.24463861589434988,"cagr_net_profit":0.33596378580758146,"cagr_investments":-0.020831622783583192,"cagr_firms":0.08034911701571379,"profit_margin_std_3y":0.10365732213053745,"size_index":5.06299615792276,"growth_index":11.62133852884855,"profit_index":80.84315635489526,"risk_index":56.91757733531557,"outlook_index":9.479676062118735,"current_index":41.20399615311517,"future_index":24.353545184096728,"main_index":34.46381576550779,"class1":null,"revenue_parameter":null,"firms_parameter":null,"growth_parameter":null,"cagr_revenue_parameter":null,"cagr_net_profit_parameter":null,"profit_margin_parameter":null,"profitable_share_parameter":null,"leverage_bank_to_rev_parameter":null,"leverage_tot_to_rev_parameter":null,"profit_margin_std_3y_parameter":null,"invest_intensity_parameter":null,"cagr_investments_parameter":null,"size_index_parameter":null,"growth_index_parameter":null,"profit_index_parameter":null,"risk_index_parameter":null,"growth_index_parameter2":null,"profit_index_parameter2":null,"risk_index_parameter2":null,"future_growth_index_parameter":null,"outlook_index_parameter":null,"future_risk_index_parameter":null,"current_index_parameter":null,"future_index_parameter":null,"prediction":null},{"id":"42e30235-758e-4310-b78a-44aee58d88a7","date":"2019","pkd":"70","pkd_name":"DZIAŁALNOŚĆ FIRM CENTRALNYCH (HEAD OFFICES); DORADZTWO ZWIĄZANE Z ZARZĄDZANIEM","year":"2019","revenue":51930.67,"net_profit":7732.2,"investments":1870.72,"firms":1877,"profitable_firms":1469,"profit_margin":0.1488946705289957,"profitable_share":0.7826318593500267,"bank_debt":30254.99,"total_liab":64306.64,"leverage_bank_to_rev":0.5826034980869687,"leverage_tot_to_rev":1.2383171640188737,"invest_intensity":0.03602341352422374,"cagr_revenue":0.031584481035557666,"cagr_net_profit":0.4445567873334797,"cagr_investments":0.0720573513844267,"cagr_firms":0.057093636514067736,"profit_margin_std_3y":0.08379307550842623,"size_index":5.610738844516823,"growth_index":46.203337058322425,"profit_index":92.94930935457464,"risk_index":62.4187943309045,"outlook_index":18.77788859894171,"current_index":54.63594767139898,"future_index":40.09779485634476,"main_index":48.82068654537729,"class1":null,"revenue_parameter":null,"firms_parameter":null,"growth_parameter":null,"cagr_revenue_parameter":null,"cagr_net_profit_parameter":null,"profit_margin_parameter":null,"profitable_share_parameter":null,"leverage_bank_to_rev_parameter":null,"leverage_tot_to_rev_parameter":null,"profit_margin_std_3y_parameter":null,"invest_intensity_parameter":null,"cagr_investments_parameter":null,"size_index_parameter":null,"growth_index_parameter":null,"profit_index_parameter":null,"risk_index_parameter":null,"growth_index_parameter2":null,"profit_index_parameter2":null,"risk_index_parameter2":null,"future_growth_index_parameter":null,"outlook_index_parameter":null,"future_risk_index_parameter":null,"current_index_parameter":null,"future_index_parameter":null,"prediction":null},{"id":"d6e43839-dda0-494f-8667-92cb412ffa04","date":"2020","pkd":"70","pkd_name":"DZIAŁALNOŚĆ FIRM CENTRALNYCH (HEAD OFFICES); DORADZTWO ZWIĄZANE Z ZARZĄDZANIEM","year":"2020","revenue":52213.899999999994,"net_profit":9103.23,"investments":770.21,"firms":1828,"profitable_firms":1436,"profit_margin":0.17434495412141213,"profitable_share":0.7855579868708972,"bank_debt":34520.23,"total_liab":190290.26,"leverage_bank_to_rev":0.661131039818899,"leverage_tot_to_rev":3.6444368262091134,"invest_intensity":0.014751052880554796,"cagr_revenue":0.09204017352654525,"cagr_net_profit":-0.023815902190964522,"cagr_investments":-0.1584764889050717,"cagr_firms":0.04173052587271431,"profit_margin_std_3y":0.050466015351329746,"size_index":5.58921233609567,"growth_index":16.052075703933617,"profit_index":91.21803380256651,"risk_index":73.05926414247642,"outlook_index":17.353867581262193,"current_index":49.853149086587095,"future_index":33.67494898642789,"main_index":43.38186904652341,"class1":null,"revenue_parameter":null,"firms_parameter":null,"growth_parameter":null,"cagr_revenue_parameter":null,"cagr_net_profit_parameter":null,"profit_margin_parameter":null,"profitable_share_parameter":null,"leverage_bank_to_rev_parameter":null,"leverage_tot_to_rev_parameter":null,"profit_margin_std_3y_parameter":null,"invest_intensity_parameter":null,"cagr_investments_parameter":null,"size_index_parameter":null,"growth_index_parameter":null,"profit_index_parameter":null,"risk_index_parameter":null,"growth_index_parameter2":null,"profit_index_parameter2":null,"risk_index_parameter2":null,"future_growth_index_parameter":null,"outlook_index_parameter":null,"future_risk_index_parameter":null,"current_index_parameter":null,"future_index_parameter":null,"prediction":null},{"id":"ae1ac3bd-bf85-4f29-9304-5109d914438a","date":"2021","pkd":"70","pkd_name":"DZIAŁALNOŚĆ FIRM CENTRALNYCH (HEAD OFFICES); DORADZTWO ZWIĄZANE Z ZARZĄDZANIEM","year":"2021","revenue":65538.20999999999,"net_profit":12449.810000000001,"investments":1165.58,"firms":1901,"profitable_firms":1531,"profit_margin":0.18996261875324338,"profitable_share":0.805365597054182,"bank_debt":29326.8,"total_liab":213334.68,"leverage_bank_to_rev":0.447476365314219,"leverage_tot_to_rev":3.2551191129571593,"invest_intensity":0.017784739619833987,"cagr_revenue":0.10791908549280271,"cagr_net_profit":0.4968177683219641,"cagr_investments":-0.08789938041261824,"cagr_firms":0.037749663160080216,"profit_margin_std_3y":0.020729225563747213,"size_index":5.888421320001443,"growth_index":47.447495361246965,"profit_index":81.10136389508361,"risk_index":81.10653832288611,"outlook_index":12.369468024832635,"current_index":57.64686057494876,"future_index":43.51399731517297,"main_index":51.99371527103845,"class1":null,"revenue_parameter":null,"firms_parameter":null,"growth_parameter":null,"cagr_revenue_parameter":null,"cagr_net_profit_parameter":null,"profit_margin_parameter":null,"profitable_share_parameter":null,"leverage_bank_to_rev_parameter":null,"leverage_tot_to_rev_parameter":null,"profit_margin_std_3y_parameter":null,"invest_intensity_parameter":null,"cagr_investments_parameter":null,"size_index_parameter":null,"growth_index_parameter":null,"profit_index_parameter":null,"risk_index_parameter":null,"growth_index_parameter2":null,"profit_index_parameter2":null,"risk_index_parameter2":null,"future_growth_index_parameter":null,"outlook_index_parameter":null,"future_risk_index_parameter":null,"current_index_parameter":null,"future_index_parameter":null,"prediction":null},{"id":"6bd37fad-6c02-4c76-a46f-9c1d7246ad98","date":"2022","pkd":"70","pkd_name":"DZIAŁALNOŚĆ FIRM CENTRALNYCH (HEAD OFFICES); DORADZTWO ZWIĄZANE Z ZARZĄDZANIEM","year":"2022","revenue":77464.32,"net_profit":12710.16,"investments":1733.67,"firms":1992,"profitable_firms":1593,"profit_margin":0.1640776037277549,"profitable_share":0.7996987951807228,"bank_debt":25955.59,"total_liab":223339.24,"leverage_bank_to_rev":0.33506509835754056,"leverage_tot_to_rev":2.8831239982484838,"invest_intensity":0.022380239057155603,"cagr_revenue":0.14259572728223024,"cagr_net_profit":0.18018288689835815,"cagr_investments":-0.025042057576769583,"cagr_firms":0.020019216868649714,"profit_margin_std_3y":0.013034338849926701,"size_index":5.985992153395195,"growth_index":30.3326048927142,"profit_index":82.59226513585944,"risk_index":81.37918018419839,"outlook_index":10.876459575184725,"current_index":53.84216999308197,"future_index":37.86411935314767,"main_index":47.450949737108246,"class1":null,"revenue_parameter":null,"firms_parameter":null,"growth_parameter":null,"cagr_revenue_parameter":null,"cagr_net_profit_parameter":null,"profit_margin_parameter":null,"profitable_share_parameter":null,"leverage_bank_to_rev_parameter":null,"leverage_tot_to_rev_parameter":null,"profit_margin_std_3y_parameter":null,"invest_intensity_parameter":null,"cagr_investments_parameter":null,"size_index_parameter":null,"growth_index_parameter":null,"profit_index_parameter":null,"risk_index_parameter":null,"growth_index_parameter2":null,"profit_index_parameter2":null,"risk_index_parameter2":null,"future_growth_index_parameter":null,"outlook_index_parameter":null,"future_risk_index_parameter":null,"current_index_parameter":null,"future_index_parameter":null,"prediction":null},{"id":"06e15188-4624-49b3-a93b-6a153559e012","date":"2023","pkd":"70","pkd_name":"DZIAŁALNOŚĆ FIRM CENTRALNYCH (HEAD OFFICES); DORADZTWO ZWIĄZANE Z ZARZĄDZANIEM","year":"2023","revenue":86195.14,"net_profit":13892.7,"investments":1733.62,"firms":2133,"profitable_firms":1720,"profit_margin":0.16117730071556238,"profitable_share":0.8063759962494139,"bank_debt":27397.76,"total_liab":225851.78,"leverage_bank_to_rev":0.31785736411588866,"leverage_tot_to_rev":2.6202379855755207,"invest_intensity":0.020112734894333947,"cagr_revenue":0.18185867893569063,"cagr_net_profit":0.15132264653672634,"cagr_investments":0.31053387710799596,"cagr_firms":0.052781443402129646,"profit_margin_std_3y":0.015848450476112497,"size_index":6.494881230246975,"growth_index":44.780075891949714,"profit_index":84.72892256394664,"risk_index":81.42082155845296,"outlook_index":20.68130310238107,"current_index":58.10247232755937,"future_index":46.132790476073225,"main_index":53.31459958696491,"class1":null,"revenue_parameter":null,"firms_parameter":null,"growth_parameter":null,"cagr_revenue_parameter":null,"cagr_net_profit_parameter":null,"profit_margin_parameter":null,"profitable_share_parameter":null,"leverage_bank_to_rev_parameter":null,"leverage_tot_to_rev_parameter":null,"profit_margin_std_3y_parameter":null,"invest_intensity_parameter":null,"cagr_investments_parameter":null,"size_index_parameter":null,"growth_index_parameter":null,"profit_index_parameter":null,"risk_index_parameter":null,"growth_index_parameter2":null,"profit_index_parameter2":null,"risk_index_parameter2":null,"future_growth_index_parameter":null,"outlook_index_parameter":null,"future_risk_index_parameter":null,"current_index_parameter":null,"future_index_parameter":null,"prediction":null},{"id":"30e56e08-c9a4-44b2-abaa-1cd515cf4ced","date":"2024","pkd":"70","pkd_name":"DZIAŁALNOŚĆ FIRM CENTRALNYCH (HEAD OFFICES); DORADZTWO ZWIĄZANE Z ZARZĄDZANIEM","year":"2024","revenue":100312.88,"net_profit":14846.57,"investments":4664.5,"firms":2194,"profitable_firms":1802,"profit_margin":0.14800262937321707,"profitable_share":0.821330902461258,"bank_debt":33972.76,"total_liab":215505.97999999998,"leverage_bank_to_rev":0.33866797563782436,"leverage_tot_to_rev":2.148338079815872,"invest_intensity":0.04649951232583493,"cagr_revenue":0.1524463264362821,"cagr_net_profit":0.0604441538863445,"cagr_investments":0.5876484248838547,"cagr_firms":0.04894206536633705,"profit_margin_std_3y":0.00856726836123391,"size_index":6.8812501160477755,"growth_index":66.83797432330395,"profit_index":89.7763065870368,"risk_index":84.4216619231691,"outlook_index":31.133808114021573,"current_index":65.85631882774547,"future_index":57.831414119550544,"main_index":62.6463569444675,"class1":null,"revenue_parameter":null,"firms_parameter":null,"growth_parameter":null,"cagr_revenue_parameter":null,"cagr_net_profit_parameter":null,"profit_margin_parameter":null,"profitable_share_parameter":null,"leverage_bank_to_rev_parameter":null,"leverage_tot_to_rev_parameter":null,"profit_margin_std_3y_parameter":null,"invest_intensity_parameter":null,"cagr_investments_parameter":null,"size_index_parameter":null,"growth_index_parameter":null,"profit_index_parameter":null,"risk_index_parameter":null,"growth_index_parameter2":null,"profit_index_parameter2":null,"risk_index_parameter2":null,"future_growth_index_parameter":null,"outlook_index_parameter":null,"future_risk_index_parameter":null,"current_index_parameter":null,"future_index_parameter":null,"prediction":null},{"id":"3b00ef37-3f43-4a58-bcd3-c5a2894b4573","date":"2025","pkd":"70","pkd_name":"","year":"2025","revenue":null,"net_profit":null,"investments":null,"firms":null,"profitable_firms":null,"profit_margin":null,"profitable_share":null,"bank_debt":null,"total_liab":null,"leverage_bank_to_rev":null,"leverage_tot_to_rev":null,"invest_intensity":null,"cagr_revenue":null,"cagr_net_profit":null,"cagr_investments":null,"cagr_firms":null,"profit_margin_std_3y":null,"size_index":null,"growth_index":null,"profit_index":null,"risk_index":null,"outlook_index":null,"current_index":null,"future_index":null,"main_index":41.84792018396314,"class1":null,"revenue_parameter":null,"firms_parameter":null,"growth_parameter":null,"cagr_revenue_parameter":null,"cagr_net_profit_parameter":null,"profit_margin_parameter":null,"profitable_share_parameter":null,"leverage_bank_to_rev_parameter":null,"leverage_tot_to_rev_parameter":null,"profit_margin_std_3y_parameter":null,"invest_intensity_parameter":null,"cagr_investments_parameter":null,"size_index_parameter":null,"growth_index_parameter":null,"profit_index_parameter":null,"risk_index_parameter":null,"growth_index_parameter2":null,"profit_index_parameter2":null,"risk_index_parameter2":null,"future_growth_index_parameter":null,"outlook_index_parameter":null,"future_risk_index_parameter":null,"current_index_parameter":null,"future_index_parameter":null,"prediction":null},{"id":"71353c05-1d45-473d-853e-2f2269411b59","date":"2026","pkd":"70","pkd_name":"","year":"2026","revenue":null,"net_profit":null,"investments":null,"firms":null,"profitable_firms":null,"profit_margin":null,"profitable_share":null,"bank_debt":null,"total_liab":null,"leverage_bank_to_rev":null,"leverage_tot_to_rev":null,"invest_intensity":null,"cagr_revenue":null,"cagr_net_profit":null,"cagr_investments":null,"cagr_firms":null,"profit_margin_std_3y":null,"size_index":null,"growth_index":null,"profit_index":null,"risk_index":null,"outlook_index":null,"current_index":null,"future_index":null,"main_index":42.120468850025134,"class1":null,"revenue_parameter":null,"firms_parameter":null,"growth_parameter":null,"cagr_revenue_parameter":null,"cagr_net_profit_parameter":null,"profit_margin_parameter":null,"profitable_share_parameter":null,"leverage_bank_to_rev_parameter":null,"leverage_tot_to_rev_parameter":null,"profit_margin_std_3y_parameter":null,"invest_intensity_parameter":null,"cagr_investments_parameter":null,"size_index_parameter":null,"growth_index_parameter":null,"profit_index_parameter":null,"risk_index_parameter":null,"growth_index_parameter2":null,"profit_index_parameter2":null,"risk_index_parameter2":null,"future_growth_index_parameter":null,"outlook_index_parameter":null,"future_risk_index_parameter":null,"current_index_parameter":null,"future_index_parameter":null,"prediction":null},{"id":"5cbd9b81-7594-4e2f-8bb5-942070610ef1","date":"2027","pkd":"70","pkd_name":"","year":"2027","revenue":null,"net_profit":null,"investments":null,"firms":null,"profitable_firms":null,"profit_margin":null,"profitable_share":null,"bank_debt":null,"total_liab":null,"leverage_bank_to_rev":null,"leverage_tot_to_rev":null,"invest_intensity":null,"cagr_revenue":null,"cagr_net_profit":null,"cagr_investments":null,"cagr_firms":null,"profit_margin_std_3y":null,"size_index":null,"growth_index":null,"profit_index":null,"risk_index":null,"outlook_index":null,"current_index":null,"future_index":null,"main_index":42.39301751608713,"class1":null,"revenue_parameter":null,"firms_parameter":null,"growth_parameter":null,"cagr_revenue_parameter":null,"cagr_net_profit_parameter":null,"profit_margin_parameter":null,"profitable_share_parameter":null,"leverage_bank_to_rev_parameter":null,"leverage_tot_to_rev_parameter":null,"profit_margin_std_3y_parameter":null,"invest_intensity_parameter":null,"cagr_investments_parameter":null,"size_index_parameter":null,"growth_index_parameter":null,"profit_index_parameter":null,"risk_index_parameter":null,"growth_index_parameter2":null,"profit_index_parameter2":null,"risk_index_parameter2":null,"future_growth_index_parameter":null,"outlook_index_parameter":null,"future_risk_index_parameter":null,"current_index_parameter":null,"future_index_parameter":null,"prediction":null}]